ccf_streamlines/__init__.py
ccf_streamlines/angle.py
ccf_streamlines/coordinates.py
ccf_streamlines/dataset.py
ccf_streamlines/linestring3d.py
ccf_streamlines/metrics.py
ccf_streamlines/morphology.py
ccf_streamlines/processing.py
ccf_streamlines/projection.py
ccf_streamlines-1.1.4.dist-info/LICENSE
ccf_streamlines-1.1.4.dist-info/METADATA
ccf_streamlines-1.1.4.dist-info/WHEEL
ccf_streamlines-1.1.4.dist-info/top_level.txt
ccf_streamlines-1.1.4.dist-info/RECORD
