Metadata-Version: 2.1
Name: ccf_streamlines
Version: 1.1.4
Summary: Projection of Allen CCF data via streamlines
Home-page: https://github.com/AllenInstitute/ccf_streamlines
Classifier: Programming Language :: Python :: 3
Requires-Python: >=3.9
License-File: LICENSE
Requires-Dist: numpy
Requires-Dist: scipy
Requires-Dist: pynrrd
Requires-Dist: h5py >=2.10
Requires-Dist: scikit-image
Requires-Dist: pandas
Requires-Dist: tqdm
